googleauth/__init__.py
googleauth/googleauth.py
scrapy_googleauth-0.1.1.dist-info/METADATA
scrapy_googleauth-0.1.1.dist-info/WHEEL
scrapy_googleauth-0.1.1.dist-info/top_level.txt
scrapy_googleauth-0.1.1.dist-info/RECORD
