Metadata-Version: 2.1
Name: scrapy-googleauth
Version: 0.1.1
Summary: google auth downloader middleware for scrapy
Home-page: https://github.com/geek-dc/scrapy-googleauth
Author: derekchan
Author-email: dchan0831@gmail.com
License: MIT Licence
Keywords: pip,datacanvas,eds,xiaoh
Platform: any
Requires-Dist: oauth2client
